[
  {
    "id": "bogota-coffee-5",
    "title": "Bogotá & Coffee Region",
    "duration": "5 days",
    "route": "Bogotá → Salento → Cocora Valley",
    "highlights": ["Museo del Oro", "Monserrate sunset", "La Candelaria street art", "Cocora Valley wax palms", "Coffee finca tour", "Salento plaza"],
    "difficulty": "Easy–Moderate",
    "bestFor": "First-timers & coffee lovers",
    "emoji": "☕",
    "popular": true,
    "destinations": 2,
    "activities": 14,
    "destinationSlugs": ["bogota", "salento"]
  },
  {
    "id": "caribbean-highlights-7",
    "title": "Caribbean Coast Explorer",
    "duration": "7 days",
    "route": "Cartagena → Santa Marta → Tayrona",
    "highlights": ["Walled City of Cartagena", "Castillo San Felipe", "Getsemaní nightlife", "Tayrona National Park", "Minca coffee village", "Playa Cristal"],
    "difficulty": "Easy–Moderate",
    "bestFor": "Beach lovers & history buffs",
    "emoji": "🏖️",
    "popular": true,
    "destinations": 2,
    "activities": 18,
    "destinationSlugs": ["cartagena", "santa-marta"]
  },
  {
    "id": "medellin-weekend-4",
    "title": "Medellín City Break",
    "duration": "4 days",
    "route": "Medellín → Guatapé",
    "highlights": ["Comuna 13 graffiti tour", "Plaza Botero", "MetroCable over the valley", "Piedra del Peñol climb", "El Poblado dining", "Jardín Botánico"],
    "difficulty": "Easy",
    "bestFor": "City lovers & culture seekers",
    "emoji": "🎨",
    "popular": true,
    "destinations": 1,
    "activities": 12,
    "destinationSlugs": ["medellin"]
  },
  {
    "id": "lost-city-trek-6",
    "title": "Lost City Trek",
    "duration": "6 days",
    "route": "Santa Marta → Ciudad Perdida → Minca",
    "highlights": ["Ciudad Perdida (Lost City) 4-day trek", "Sierra Nevada mountain crossing", "Indigenous Kogi communities", "Minca waterfalls & coffee", "Taganga diving", "Palomino beach"],
    "difficulty": "Challenging",
    "bestFor": "Adventurers & trekkers",
    "emoji": "🏔️",
    "popular": true,
    "destinations": 1,
    "activities": 14,
    "destinationSlugs": ["santa-marta"]
  },
  {
    "id": "island-paradise-5",
    "title": "San Andrés & Providencia Islands",
    "duration": "5 days",
    "route": "San Andrés → Providencia",
    "highlights": ["Sea of seven colors", "Johnny Cay island", "Hoyo Soplador", "Crab Cay snorkeling", "The Peak hike", "Reggae & Raizal culture"],
    "difficulty": "Easy",
    "bestFor": "Beach lovers & divers",
    "emoji": "🏝️",
    "popular": true,
    "destinations": 2,
    "activities": 14,
    "destinationSlugs": ["san-andres", "providencia"]
  },
  {
    "id": "colonial-villages-5",
    "title": "Colonial Villages Trail",
    "duration": "5 days",
    "route": "Bogotá → Villa de Leyva → Barichara",
    "highlights": ["Plaza Mayor cobblestones", "Fossil museum", "Camino Real to Guane", "Chicamocha Canyon", "Casa Terracota", "Ráquira pottery village"],
    "difficulty": "Easy–Moderate",
    "bestFor": "History buffs & slow travelers",
    "emoji": "🏘️",
    "popular": false,
    "destinations": 3,
    "activities": 14,
    "destinationSlugs": ["bogota", "villa-de-leyva", "barichara"]
  },
  {
    "id": "salsa-cali-3",
    "title": "Cali Salsa & Culture",
    "duration": "3 days",
    "route": "Cali",
    "highlights": ["Salsa dancing at Tin Tin Deo", "Cristo Rey hilltop", "San Antonio neighborhood", "Gato del Río cat sculptures", "La Merced church", "Pacific coast seafood"],
    "difficulty": "Easy",
    "bestFor": "Dance lovers & foodies",
    "emoji": "💃",
    "popular": false,
    "destinations": 1,
    "activities": 10,
    "destinationSlugs": ["cali"]
  },
  {
    "id": "grand-colombia-14",
    "title": "Grand Colombia",
    "duration": "14 days",
    "route": "Bogotá → Medellín → Coffee Region → Cartagena → Santa Marta → San Andrés",
    "highlights": ["Museo del Oro", "Comuna 13", "Cocora Valley", "Walled City", "Tayrona Park", "Johnny Cay", "Monserrate sunset", "Guatapé"],
    "difficulty": "Moderate",
    "bestFor": "Deep explorers & long-trip travelers",
    "emoji": "🌍",
    "popular": false,
    "destinations": 6,
    "activities": 30,
    "destinationSlugs": ["bogota", "medellin", "salento", "cartagena", "santa-marta", "san-andres"]
  }
]
